<?xml version="1.0" encoding="UTF-8"?>
<root>
	<equip id="7001" name="直刀" part="0" kind="">
		<des></des>
		<useCase value="" />
		<eff value="atk:8-12;" />
		<acs>
			<ac></ac>
		</acs>
	</equip>
	<equip id="7002" name="钢刀" part="0" kind="">
		<des></des>
		<useCase value="" />
		<eff value="atk:12-20;" />
		<acs>
			<ac></ac>
		</acs>
	</equip>
	<equip id="7003" name="百炼刀" part="0" kind="">
		<des></des>
		<useCase value="" />
		<eff value="atk:18-31;" />
		<acs>
			<ac></ac>
		</acs>
	</equip>
	<equip id="7004" name="半月" part="0" kind="">
		<des></des>
		<useCase value="" />
		<eff value="atk:24-37;" />
		<acs>
			<ac></ac>
		</acs>
	</equip>
	<equip id="7005" name="赤霞刀" part="0" kind="">
		<des></des>
		<useCase value="" />
		<eff value="atk:32-53;" />
		<acs>
			<ac></ac>
		</acs>
	</equip>
	<equip id="7006" name="渤海刀" part="0" kind="">
		<des></des>
		<useCase value="" />
		<eff value="atk:40-61;" />
		<acs>
			<ac></ac>
		</acs>
	</equip>
	<equip id="7007" name="花翎刀" part="0" kind="">
		<des></des>
		<useCase value="" />
		<eff value="atk:50-75;" />
		<acs>
			<ac></ac>
		</acs>
	</equip>
	<equip id="7008" name="破军" part="0" kind="">
		<des></des>
		<useCase value="" />
		<eff value="atk:62-83;" />
		<acs>
			<ac></ac>
		</acs>
	</equip>
	<equip id="7009" name="断水" part="0" kind="">
		<des></des>
		<useCase value="" />
		<eff value="atk:78-98;" />
		<acs>
			<ac></ac>
		</acs>
	</equip>
	<equip id="7010" name="磐龙刀" part="0" kind="">
		<des></des>
		<useCase value="" />
		<eff value="atk:95-114;" />
		<acs>
			<ac></ac>
		</acs>
	</equip>
	
	
	<equip id="7011" name="铁剑" part="0" kind="">
		<des></des>
		<useCase value="" />
		<eff value="atk:10-15;" />
		<acs>
			<ac></ac>
		</acs>
	</equip>
	<equip id="7012" name="精钢剑" part="0" kind="">
		<des></des>
		<useCase value="" />
		<eff value="atk:15-25;" />
		<acs>
			<ac></ac>
		</acs>
	</equip>
	<equip id="7013" name="水月剑" part="0" kind="">
		<des></des>
		<useCase value="" />
		<eff value="atk:22-35;" />
		<acs>
			<ac></ac>
		</acs>
	</equip>
	<equip id="7014" name="飞花剑" part="0" kind="">
		<des></des>
		<useCase value="" />
		<eff value="atk:28-43;" />
		<acs>
			<ac></ac>
		</acs>
	</equip>
	<equip id="7015" name="赤星剑" part="0" kind="">
		<des></des>
		<useCase value="" />
		<eff value="atk:36-50;" />
		<acs>
			<ac></ac>
		</acs>
	</equip>
	<equip id="7016" name="青锋剑" part="0" kind="">
		<des></des>
		<useCase value="" />
		<eff value="atk:48-62;" />
		<acs>
			<ac></ac>
		</acs>
	</equip>
	<equip id="7017" name="流光剑" part="0" kind="">
		<des></des>
		<useCase value="" />
		<eff value="atk:60-74;" />
		<acs>
			<ac></ac>
		</acs>
	</equip>
	<equip id="7018" name="飞虹剑" part="0" kind="">
		<des></des>
		<useCase value="" />
		<eff value="atk:72-87;" />
		<acs>
			<ac></ac>
		</acs>
	</equip>
	<equip id="7019" name="落英剑" part="0" kind="">
		<des></des>
		<useCase value="" />
		<eff value="atk:88-103;" />
		<acs>
			<ac></ac>
		</acs>
	</equip>
	<equip id="7020" name="无影 " part="0" kind="">
		<des></des>
		<useCase value="" />
		<eff value="atk:104-119;" />
		<acs>
			<ac></ac>
		</acs>
	</equip>
	
	
	
</root>